ansible_galaxy_outdated/__init__.py
ansible_galaxy_outdated-1.2.1.dist-info/COPYING
ansible_galaxy_outdated-1.2.1.dist-info/METADATA
ansible_galaxy_outdated-1.2.1.dist-info/WHEEL
ansible_galaxy_outdated-1.2.1.dist-info/entry_points.txt
ansible_galaxy_outdated-1.2.1.dist-info/top_level.txt
ansible_galaxy_outdated-1.2.1.dist-info/RECORD
