Metadata-Version: 2.1
Name: ansible-galaxy-outdated
Version: 1.2.1
Summary: Shows currently installed Ansible collections with updated version in Ansible Galaxy
Author: Christian Loos
Author-email: cloos@netsandbox.de
License: GPLv3+
Project-URL: Changelog, https://github.com/netsandbox/ansible-galaxy-outdated/releases
Project-URL: Documentation, https://github.com/netsandbox/ansible-galaxy-outdated
Project-URL: Homepage, https://github.com/netsandbox/ansible-galaxy-outdated
Project-URL: Issues, https://github.com/netsandbox/ansible-galaxy-outdated/issues
Project-URL: Source, https://github.com/netsandbox/ansible-galaxy-outdated
Classifier: Development Status :: 5 - Production/Stable
Classifier: Environment :: Console
Classifier: Intended Audience :: Developers
Classifier: Intended Audience :: Information Technology
Classifier: Intended Audience :: System Administrators
Classifier: License :: OSI Approved :: GNU General Public License v3 or later (GPLv3+)
Classifier: Natural Language :: English
Classifier: Operating System :: POSIX
Classifier: Programming Language :: Python :: 3
Classifier: Programming Language :: Python :: 3.8
Classifier: Programming Language :: Python :: 3.9
Classifier: Programming Language :: Python :: 3.10
Classifier: Programming Language :: Python :: 3.11
Classifier: Programming Language :: Python :: 3 :: Only
Classifier: Topic :: System :: Installation/Setup
Classifier: Topic :: System :: Systems Administration
Classifier: Topic :: Utilities
Requires-Python: >=3.8
License-File: COPYING
